json2df/__init__.py
json2df/base.py
json2df-0.1.4.2.dist-info/DESCRIPTION.rst
json2df-0.1.4.2.dist-info/METADATA
json2df-0.1.4.2.dist-info/RECORD
json2df-0.1.4.2.dist-info/WHEEL
json2df-0.1.4.2.dist-info/metadata.json
json2df-0.1.4.2.dist-info/top_level.txt
