Metadata-Version: 2.0
Name: json2df
Version: 0.1.4.2
Summary: convert json data to Pandas DataFrame
Home-page: https://github.com/shichaoji/json2df
Author: Shichao(Richard) Ji
Author-email: jshichao@vt.edu
License: MIT
Download-URL: https://github.com/shichaoji/json2df/archive/0.1.1.tar.gz
Keywords: data,json,dataframe,python
Platform: UNKNOWN
Classifier: License :: OSI Approved :: MIT License
Classifier: Programming Language :: Python :: 2
Classifier: Programming Language :: Python :: 3
Requires-Dist: pandas
